glab_preset/main.py
glab_preset/presets/__init__.py
glab_preset/presets/misc.py
glab_preset/presets/react_k8s.py
glab_preset/presets/react_oss.py
glab_preset-1.0.15.dist-info/entry_points.txt
glab_preset-1.0.15.dist-info/WHEEL
glab_preset-1.0.15.dist-info/METADATA
glab_preset-1.0.15.dist-info/RECORD
