Metadata-Version: 2.1
Name: glab-preset
Version: 1.0.15
Summary: Gitlab preset tool.
License: MIT
Author: afeiship
Author-email: 1290657123@qq.com
Requires-Python: >=3.8,<4.0
Classifier: License :: OSI Approved :: MIT License
Classifier: Programming Language :: Python :: 3
Classifier: Programming Language :: Python :: 3.8
Classifier: Programming Language :: Python :: 3.9
Classifier: Programming Language :: Python :: 3.10
Requires-Dist: click (>=8.1.3,<9.0.0)
Requires-Dist: python-gitlab (>=3.5.0,<4.0.0)
